Workbook

Sheet 📊 Dashboard
A1: 🖨️ MANAJEMEN KEUANGAN - PERCETAKAN SABLON KAOS
A2: Template Keuangan | Periode: Isi Bulan/Tahun
A4: RINGKASAN KEUANGAN BULAN INI
A5: Total Pendapatan | C5: Total HPP | E5: Laba Kotor | G5: Total Beban | I5: Laba Bersih
A7: ='📈 Penjualan'!M3 -> 0 | C7: ='⚙️ Produksi'!J3 -> 22500 | E7: =B7-D7 -> 0 | G7: ='💼 Beban Operasional'!E3 -> 8000000 | I7: =F7-H7 -> 0
A9: NAVIGASI SHEET
A10: 📈 Penjualan | B10: Catat semua transaksi penjualan & order
A11: 💰 Kas & Bank | B11: Mutasi kas harian dan saldo bank
A12: 📦 Pembelian Bahan | B12: Pembelian bahan baku & supplies
A13: ⚙️ Produksi | B13: HPP dan biaya produksi per order
A14: 👥 Piutang Pelanggan | B14: Tagihan & status pembayaran pelanggan
A15: 🏢 Hutang Supplier | B15: Hutang & jatuh tempo ke supplier
A16: 💼 Beban Operasional | B16: Gaji, sewa, utilitas, dll.
A17: 📋 Laporan Laba Rugi | B17: Laporan Laba Rugi bulanan
A18: 🏦 Neraca | B18: Posisi keuangan perusahaan

Sheet 📈 Penjualan
A1: 📈 CATATAN PENJUALAN & ORDER
A2: No | B2: Tgl Order | C2: No. Invoice | D2: Nama Pelanggan | E2: Jenis Produk | F2: Qty (pcs) | G2: Harga Satuan (Rp) | H2: Total Harga (Rp) | I2: DP Diterima (Rp) | J2: Sisa Tagihan (Rp) | K2: Tgl Lunas | L2: Status | M2: Keterangan
A3: 1 | B3: 45658 | C3: INV-2025-001 | D3: CV Maju Bersama | E3: Kaos Sablon Manual | F3: 50 | G3: 35000 | H3: =F3*G3 -> 1750000 | I3: =IF(L3="LUNAS",H3,H3*0.5) -> 1750000 | J3: =H3-I3 -> 0 | K3: 45672 | L3: LUNAS
A4: 2 | B4: 45659 | C4: INV-2025-002 | D4: Toko Seragam Jaya | E4: Kaos DTF | F4: 100 | G4: 40000 | H4: =F4*G4 -> 4000000 | I4: =IF(L4="LUNAS",H4,H4*0.5) -> 2000000 | J4: =H4-I4 -> 2000000 | L4: DP 50%
A5: 3 | B5: 45660 | C5: INV-2025-003 | D5: PT Abadi Karya | E5: Kaos DTG | F5: 150 | G5: 45000 | H5: =F5*G5 -> 6750000 | I5: =IF(L5="LUNAS",H5,H5*0.5) -> 3375000 | J5: =H5-I5 -> 3375000 | K5: 45674 | L5: BELUM BAYAR
A6: 4 | B6: 45661 | C6: INV-2025-004 | D6: Yayasan Bakti | E6: Polo Bordir | F6: 200 | G6: 50000 | H6: =F6*G6 -> 10000000 | I6: =IF(L6="LUNAS",H6,H6*0.5) -> 10000000 | J6: =H6-I6 -> 0 | L6: LUNAS
A7: 5 | B7: 45662 | C7: INV-2025-005 | D7: Koperasi Sejahtera | E7: Kaos Polos | F7: 250 | G7: 55000 | H7: =F7*G7 -> 13750000 | I7: =IF(L7="LUNAS",H7,H7*0.5) -> 6875000 | J7: =H7-I7 -> 6875000 | K7: 45676 | L7: DP 50%
A8: 6 | B8: 45663 | C8: INV-2025-006 | D8: CV Maju Bersama | E8: Kaos Sablon Manual | F8: 300 | G8: 60000 | H8: =F8*G8 -> 18000000 | I8: =IF(L8="LUNAS",H8,H8*0.5) -> 18000000 | J8: =H8-I8 -> 0 | L8: LUNAS
A9: 7 | B9: 45664 | C9: INV-2025-007 | D9: Toko Seragam Jaya | E9: Kaos DTF | F9: 350 | G9: 65000 | H9: =F9*G9 -> 22750000 | I9: =IF(L9="LUNAS",H9,H9*0.5) -> 11375000 | J9: =H9-I9 -> 11375000 | K9: 45678 | L9: DP 50%
A10: 8 | B10: 45665 | C10: INV-2025-008 | D10: PT Abadi Karya | E10: Kaos DTG | F10: 400 | G10: 70000 | H10: =F10*G10 -> 28000000 | I10: =IF(L10="LUNAS",H10,H10*0.5) -> 14000000 | J10: =H10-I10 -> 14000000 | L10: BELUM BAYAR
A11: 9 | B11: 45666 | C11: INV-2025-009 | D11: Yayasan Bakti | E11: Polo Bordir | F11: 450 | G11: 75000 | H11: =F11*G11 -> 33750000 | I11: =IF(L11="LUNAS",H11,H11*0.5) -> 33750000 | J11: =H11-I11 -> 0 | K11: 45680 | L11: LUNAS
A12: 10 | B12: 45667 | C12: INV-2025-010 | D12: Koperasi Sejahtera | E12: Kaos Polos | F12: 500 | G12: 80000 | H12: =F12*G12 -> 40000000 | I12: =IF(L12="LUNAS",H12,H12*0.5) -> 20000000 | J12: =H12-I12 -> 20000000 | L12: DP 50%
A13: TOTAL | F13: =SUM(F3:F12) -> 2750 | G13: =SUM(G3:G12) -> 575000 | H13: =SUM(H3:H12) -> 178750000 | I13: =SUM(I3:I12) -> 121125000 | J13: =SUM(J3:J12) -> 57625000

Sheet 💰 Kas & Bank
A1: 💰 BUKU KAS & BANK
A2: SALDO AWAL | D2: Kas Tunai (Rp) | E2: 5000000 | F2: Bank (Rp) | G2: 25000000
A3: No | B3: Tanggal | C3: Keterangan | D3: Kategori | E3: Referensi | F3: Masuk (Rp) | G3: Keluar (Rp) | H3: Saldo Kas (Rp) | I3: Saldo Bank (Rp)
A4: 1 | B4: 01/01/2025 | C4: Saldo Awal | D4: Saldo Awal | E4: - | F4: 30000000 | H4: =E2+F4-G4 -> 35000000 | I4: =G2+SUM(F4:F4)-SUM(G4:G4) -> 55000000
A5: 2 | B5: 02/01/2025 | C5: Pembayaran Order INV-001 | D5: Penjualan | E5: INV-001 | F5: 3500000 | H5: =H4+F5-G5 -> 38500000 | I5: =G2+SUM(F4:F5)-SUM(G4:G5) -> 58500000
A6: 3 | B6: 03/01/2025 | C6: Beli Kaos Polos 200 pcs | D6: Pembelian Bahan | E6: PO-001 | G6: 2800000 | H6: =H5+F6-G6 -> 35700000 | I6: =G2+SUM(F4:F6)-SUM(G4:G6) -> 55700000
A7: 4 | B7: 04/01/2025 | C7: Beli Tinta Sablon | D7: Pembelian Bahan | E7: PO-002 | G7: 450000 | H7: =H6+F7-G7 -> 35250000 | I7: =G2+SUM(F4:F7)-SUM(G4:G7) -> 55250000
A8: 5 | B8: 05/01/2025 | C8: Gaji Karyawan Jan | D8: Gaji | E8: GAJ-001 | G8: 8000000 | H8: =H7+F8-G8 -> 27250000 | I8: =G2+SUM(F4:F8)-SUM(G4:G8) -> 47250000
A9: 6 | B9: 06/01/2025 | C9: Bayar Sewa Tempat | D9: Sewa | E9: SEW-001 | G9: 3000000 | H9: =H8+F9-G9 -> 24250000 | I9: =G2+SUM(F4:F9)-SUM(G4:G9) -> 44250000
A10: 7 | B10: 07/01/2025 | C10: DP Order INV-002 | D10: Penjualan | E10: INV-002 | F10: 5250000 | H10: =H9+F10-G10 -> 29500000 | I10: =G2+SUM(F4:F10)-SUM(G4:G10) -> 49500000
A11: 8 | B11: 08/01/2025 | C11: Listrik & Air | D11: Utilitas | E11: UTL-001 | G11: 750000 | H11: =H10+F11-G11 -> 28750000 | I11: =G2+SUM(F4:F11)-SUM(G4:G11) -> 48750000
A12: 9 | B12: 09/01/2025 | C12: Bayar Lunas INV-003 | D12: Penjualan | E12: INV-003 | F12: 7000000 | H12: =H11+F12-G12 -> 35750000 | I12: =G2+SUM(F4:F12)-SUM(G4:G12) -> 55750000
A13: 10 | B13: 10/01/2025 | C13: Beli Screen Sablon | D13: Pembelian Alat | E13: PO-003 | G13: 1200000 | H13: =H12+F13-G13 -> 34550000 | I13: =G2+SUM(F4:F13)-SUM(G4:G13) -> 54550000
A14: TOTAL PERIODE INI | F14: =SUM(F4:F13) -> 45750000 | G14: =SUM(G4:G13) -> 16200000

Sheet 📦 Pembelian Bahan
A1: 📦 PEMBELIAN BAHAN BAKU & SUPPLIES
A2: No | B2: Tanggal | C2: No. PO | D2: Nama Supplier | E2: Nama Bahan | F2: Qty | G2: Satuan | H2: Harga Satuan (Rp) | I2: Total (Rp) | J2: Jatuh Tempo | K2: Status Bayar
A3: 1 | B3: 02/01/2025 | C3: PO-001 | D3: Supplier Kaos Jaya | E3: Kaos Polos Cotton 30s | F3: 200 | G3: pcs | H3: 14000 | I3: =F3*H3 -> 2800000 | K3: LUNAS
A4: 2 | B4: 04/01/2025 | C4: PO-002 | D4: Toko Cat Sablon | E4: Tinta Plastisol Hitam | F4: 5 | G4: kg | H4: 90000 | I4: =F4*H4 -> 450000 | K4: LUNAS
A5: 3 | B5: 04/01/2025 | C5: PO-002 | D5: Toko Cat Sablon | E5: Tinta Plastisol Putih | F5: 3 | G5: kg | H5: 90000 | I5: =F5*H5 -> 270000 | K5: LUNAS
A6: 4 | B6: 08/01/2025 | C6: PO-003 | D6: UD Perlengkapan Cetak | E6: Screen/Kasa 43T | F6: 10 | G6: pcs | H6: 120000 | I6: =F6*H6 -> 1200000 | J6: 30/01/2025 | K6: KREDIT
A7: 5 | B7: 10/01/2025 | C7: PO-004 | D7: Supplier Kaos Jaya | E7: Kaos Polo Cotton Pique | F7: 100 | G7: pcs | H7: 35000 | I7: =F7*H7 -> 3500000 | J7: 30/01/2025 | K7: KREDIT
A8: 6 | B8: 12/01/2025 | C8: PO-005 | D8: Toko Packaging | E8: Plastik OPP 35x50cm | F8: 500 | G8: pcs | H8: 500 | I8: =F8*H8 -> 250000 | K8: LUNAS
A9: 7 | B9: 15/01/2025 | C9: PO-005 | D9: Toko Packaging | E9: Hangtag Custom | F9: 1000 | G9: pcs | H9: 350 | I9: =F9*H9 -> 350000 | K9: LUNAS
A10: TOTAL PEMBELIAN | I10: =SUM(I3:I9) -> 8820000

Sheet ⚙️ Produksi
A1: ⚙️ BIAYA PRODUKSI & HPP PER ORDER
A2: No | B2: No. Invoice | C2: Nama Produk | D2: Qty (pcs) | E2: Bahan Baku (Rp) | F2: Tinta/Film (Rp) | G2: TK Langsung (Rp) | H2: Overhead (Rp) | I2: Total HPP (Rp) | J2: HPP/pcs (Rp) | K2: Harga Jual (Rp) | L2: Margin (%)
A3: 1 | B3: INV-001 | C3: Kaos Sablon Manual | D3: 100 | E3: 1400000 | F3: 200000 | G3: 500000 | H3: 150000 | I3: =E3+F3+G3+H3 -> 2250000 | J3: =IF(D3>0,I3/D3,0) -> 22500 | K3: 5000000 | L3: =IF(K3>0,(K3-I3)/K3,0) -> 0.55
A4: 2 | B4: INV-002 | C4: Kaos DTF Full Color | D4: 150 | E4: 2625000 | F4: 450000 | G4: 750000 | H4: 225000 | I4: =E4+F4+G4+H4 -> 4050000 | J4: =IF(D4>0,I4/D4,0) -> 27000 | K4: 9000000 | L4: =IF(K4>0,(K4-I4)/K4,0) -> 0.55
A5: 3 | B5: INV-003 | C5: Kaos Polo Bordir | D5: 200 | E5: 7000000 | F5: 0 | G5: 1200000 | H5: 350000 | I5: =E5+F5+G5+H5 -> 8550000 | J5: =IF(D5>0,I5/D5,0) -> 42750 | K5: 16000000 | L5: =IF(K5>0,(K5-I5)/K5,0) -> 0.465625
A6: 4 | B6: INV-004 | C6: Kaos Polos Printing | D6: 50 | E6: 700000 | F6: 150000 | G6: 250000 | H6: 75000 | I6: =E6+F6+G6+H6 -> 1175000 | J6: =IF(D6>0,I6/D6,0) -> 23500 | K6: 2500000 | L6: =IF(K6>0,(K6-I6)/K6,0) -> 0.53
A7: 5 | B7: INV-005 | C7: Kaos Event Sablon 2 Warna | D7: 300 | E7: 4200000 | F7: 600000 | G7: 1500000 | H7: 450000 | I7: =E7+F7+G7+H7 -> 6750000 | J7: =IF(D7>0,I7/D7,0) -> 22500 | K7: 18000000 | L7: =IF(K7>0,(K7-I7)/K7,0) -> 0.625
A8: TOTAL | D8: =SUM(D3:D7) -> 800 | E8: =SUM(E3:E7) -> 15925000 | F8: =SUM(F3:F7) -> 1400000 | G8: =SUM(G3:G7) -> 4200000 | H8: =SUM(H3:H7) -> 1250000 | I8: =SUM(I3:I7) -> 22775000 | K8: =SUM(K3:K7) -> 50500000

Sheet 👥 Piutang Pelanggan
A1: 👥 KARTU PIUTANG PELANGGAN
A2: No | B2: Nama Pelanggan | C2: No. Invoice | D2: Tgl Invoice | E2: Total Tagihan (Rp) | F2: DP/Bayar (Rp) | G2: Sisa Piutang (Rp) | H2: Jatuh Tempo | I2: Status / Umur Piutang
A3: 1 | B3: CV Maju Bersama | C3: INV-001 | D3: 02/01/2025 | E3: 5000000 | F3: 5000000 | G3: =E3-F3 -> 0 | H3: 15/01/2025 | I3: LUNAS
A4: 2 | B4: Toko Seragam Jaya | C4: INV-002 | D4: 05/01/2025 | E4: 10500000 | F4: 5250000 | G4: =E4-F4 -> 5250000 | H4: 20/01/2025 | I4: SEBAGIAN
A5: 3 | B5: PT Abadi Karya | C5: INV-003 | D5: 07/01/2025 | E5: 16000000 | F5: 16000000 | G5: =E5-F5 -> 0 | H5: 21/01/2025 | I5: LUNAS
A6: 4 | B6: Yayasan Bakti | C6: INV-004 | D6: 10/01/2025 | E6: 2500000 | F6: 0 | G6: =E6-F6 -> 2500000 | H6: 25/01/2025 | I6: BELUM BAYAR
A7: 5 | B7: Koperasi Sejahtera | C7: INV-005 | D7: 15/01/2025 | E7: 18000000 | F7: 9000000 | G7: =E7-F7 -> 9000000 | H7: 30/01/2025 | I7: SEBAGIAN
A8: TOTAL PIUTANG | E8: =SUM(E3:E7) -> 52000000 | F8: =SUM(F3:F7) -> 35250000 | G8: =SUM(G3:G7) -> 16750000

Sheet 🏢 Hutang Supplier
A1: 🏢 KARTU HUTANG SUPPLIER
A2: No | B2: Nama Supplier | C2: No. PO | D2: Tgl PO | E2: Total Hutang (Rp) | F2: Sudah Dibayar (Rp) | G2: Sisa Hutang (Rp) | H2: Jatuh Tempo | I2: Status
A3: 1 | B3: Supplier Kaos Jaya | C3: PO-001 | D3: 02/01/2025 | E3: 2800000 | F3: 2800000 | G3: =E3-F3 -> 0 | H3: 16/01/2025 | I3: LUNAS
A4: 2 | B4: Toko Cat Sablon | C4: PO-002 | D4: 04/01/2025 | E4: 720000 | F4: 720000 | G4: =E4-F4 -> 0 | H4: 18/01/2025 | I4: LUNAS
A5: 3 | B5: UD Perlengkapan Cetak | C5: PO-003 | D5: 08/01/2025 | E5: 1200000 | F5: 0 | G5: =E5-F5 -> 1200000 | H5: 22/01/2025 | I5: BELUM BAYAR
A6: 4 | B6: Supplier Kaos Jaya | C6: PO-004 | D6: 10/01/2025 | E6: 3500000 | F6: 1750000 | G6: =E6-F6 -> 1750000 | H6: 24/01/2025 | I6: SEBAGIAN
A7: 5 | B7: Toko Packaging | C7: PO-005 | D7: 12/01/2025 | E7: 600000 | F7: 600000 | G7: =E7-F7 -> 0 | H7: 26/01/2025 | I7: LUNAS
A8: TOTAL HUTANG | E8: =SUM(E3:E7) -> 8820000 | F8: =SUM(F3:F7) -> 5870000 | G8: =SUM(G3:G7) -> 2950000

Sheet 💼 Beban Operasional
A1: 💼 BEBAN OPERASIONAL BULANAN
A2: No | B2: Tanggal | C2: Keterangan | D2: Kategori | E2: Jumlah (Rp) | F2: Bukti/Ref | G2: Keterangan
A3: 1 | B3: 05/01/2025 | C3: Gaji Karyawan Produksi (5 org) | D3: Gaji & Upah | E3: 8000000 | F3: BKT-001
A4: 2 | B4: 05/01/2025 | C4: Gaji Admin & Marketing | D4: Gaji & Upah | E4: 4000000 | F4: BKT-002
A5: 3 | B5: 10/01/2025 | C5: Sewa Tempat Usaha | D5: Sewa | E5: 3000000 | F5: BKT-003
A6: 4 | B6: 12/01/2025 | C6: Tagihan Listrik | D6: Utilitas | E6: 650000 | F6: BKT-004
A7: 5 | B7: 12/01/2025 | C7: Tagihan Air | D7: Utilitas | E7: 100000 | F7: BKT-005
A8: 6 | B8: 15/01/2025 | C8: Iklan Media Sosial | D8: Pemasaran | E8: 500000 | F8: BKT-006
A9: 7 | B9: 15/01/2025 | C9: Ongkir Sampel ke Pelanggan | D9: Pemasaran | E9: 250000 | F9: BKT-007
A10: 8 | B10: 20/01/2025 | C10: ATK & Perlengkapan Kantor | D10: Administrasi | E10: 200000 | F10: BKT-008
A11: 9 | B11: 20/01/2025 | C11: Biaya Transfer Bank | D11: Administrasi | E11: 50000 | F11: BKT-009
A12: 10 | B12: 25/01/2025 | C12: Perawatan Mesin Press | D12: Pemeliharaan | E12: 350000 | F12: BKT-010
A13: 11 | B13: 28/01/2025 | C13: Internet & Telepon | D13: Utilitas | E13: 400000 | F13: BKT-011
A14: 12 | B14: 30/01/2025 | C14: Transportasi & BBM | D14: Operasional | E14: 600000 | F14: BKT-012
A15: TOTAL BEBAN OPERASIONAL | E15: =SUM(E3:E14) -> 18100000
A17: REKAP PER KATEGORI | D17: Total (Rp) | E17: % dari Total
A18: Gaji & Upah | D18: =SUMIF(D3:D14,"Gaji & Upah",E3:E14) -> 12000000 | E18: =IF(E15>0,D18/E15,0) -> 0.66298343
A19: Sewa | D19: =SUMIF(D3:D14,"Sewa",E3:E14) -> 3000000 | E19: =IF(E15>0,D19/E15,0) -> 0.16574586
A20: Utilitas | D20: =SUMIF(D3:D14,"Utilitas",E3:E14) -> 1150000 | E20: =IF(E15>0,D20/E15,0) -> 0.063535912
A21: Pemasaran | D21: =SUMIF(D3:D14,"Pemasaran",E3:E14) -> 750000 | E21: =IF(E15>0,D21/E15,0) -> 0.041436464
A22: Administrasi | D22: =SUMIF(D3:D14,"Administrasi",E3:E14) -> 250000 | E22: =IF(E15>0,D22/E15,0) -> 0.013812155
A23: Pemeliharaan | D23: =SUMIF(D3:D14,"Pemeliharaan",E3:E14) -> 350000 | E23: =IF(E15>0,D23/E15,0) -> 0.019337017
A24: Operasional | D24: =SUMIF(D3:D14,"Operasional",E3:E14) -> 600000 | E24: =IF(E15>0,D24/E15,0) -> 0.033149171

Sheet 📋 Laporan Laba Rugi
A1: 📋 LAPORAN LABA RUGI
A2: Periode: Januari 2025
A4: I. PENDAPATAN
A5: Pendapatan Penjualan | D5: ='📈 Penjualan'!H13 -> 178750000
A6: Diskon Penjualan | D6: 0
A7: Total Pendapatan Bersih | D7: =D5-D6 -> 178750000
A9: II. HARGA POKOK PENJUALAN (HPP)
A10: Bahan Baku | D10: ='⚙️ Produksi'!E8 -> 15925000
A11: Tinta / Film | D11: ='⚙️ Produksi'!F8 -> 1400000
A12: Tenaga Kerja Langsung | D12: ='⚙️ Produksi'!G8 -> 4200000
A13: Overhead Pabrik | D13: ='⚙️ Produksi'!H8 -> 1250000
A14: Total HPP | D14: =SUM(D10:D13) -> 22775000
A16: LABA KOTOR | D16: =D7-D14 -> 155975000
A18: III. BEBAN OPERASIONAL
A19: Gaji & Upah | D19: =SUMIF('💼 Beban Operasional'!D3:D14,"Gaji & Upah",'💼 Beban Operasional'!E3:E14) -> 12000000
A20: Sewa | D20: =SUMIF('💼 Beban Operasional'!D3:D14,"Sewa",'💼 Beban Operasional'!E3:E14) -> 3000000
A21: Utilitas | D21: =SUMIF('💼 Beban Operasional'!D3:D14,"Utilitas",'💼 Beban Operasional'!E3:E14) -> 1150000
A22: Pemasaran | D22: =SUMIF('💼 Beban Operasional'!D3:D14,"Pemasaran",'💼 Beban Operasional'!E3:E14) -> 750000
A23: Administrasi | D23: =SUMIF('💼 Beban Operasional'!D3:D14,"Administrasi",'💼 Beban Operasional'!E3:E14) -> 250000
A24: Pemeliharaan | D24: =SUMIF('💼 Beban Operasional'!D3:D14,"Pemeliharaan",'💼 Beban Operasional'!E3:E14) -> 350000
A25: Operasional | D25: =SUMIF('💼 Beban Operasional'!D3:D14,"Operasional",'💼 Beban Operasional'!E3:E14) -> 600000
A26: Total Beban Operasional | D26: ='💼 Beban Operasional'!E15 -> 18100000
A28: LABA BERSIH SEBELUM PAJAK | D28: =D16-D26 -> 137875000

Sheet 🏦 Neraca
A1: 🏦 NERACA (BALANCE SHEET)
A2: Per 31 Januari 2025
A3: ASET | D3: LIABILITAS & EKUITAS
A4: Aset Lancar | D4: Liabilitas Lancar
A5: 1.1 | B5: Kas Tunai | C5: ='💰 Kas & Bank'!E2 -> 5000000 | D5: 3.1 | E5: Hutang Usaha (Supplier) | F5: ='🏢 Hutang Supplier'!G8 -> 2950000
A6: 1.2 | B6: Kas di Bank | C6: ='💰 Kas & Bank'!G2 -> 25000000 | D6: 3.2 | E6: Uang Muka Pelanggan | F6: ='📈 Penjualan'!I13 -> 121125000
A7: 1.3 | B7: Piutang Usaha | C7: ='👥 Piutang Pelanggan'!G8 -> 16750000 | D7: 3.3 | E7: Hutang Pajak | F7: 1500000
A8: 1.4 | B8: Persediaan Bahan Baku | C8: 8500000 | D8: 3.4 | E8: Biaya Yang Masih Harus Dibayar | F8: 500000
A9: 1.5 | B9: Persediaan Barang Jadi | C9: 3200000
B10: Total Aset Lancar | C10: =SUM(C5:C9) -> 58450000 | E10: Total Liabilitas Lancar | F10: =SUM(F5:F8) -> 126075000
A12: Aset Tetap | D12: Ekuitas
A13: 2.1 | B13: Mesin & Peralatan | C13: 45000000 | D13: 4.1 | E13: Modal Disetor | F13: 50000000
A14: 2.2 | B14: Akumulasi Penyusutan | C14: -9000000 | D14: 4.2 | E14: Laba Ditahan | F14: 15000000
A15: 2.3 | B15: Inventaris Kantor | C15: 5000000 | D15: 4.3 | E15: Laba Berjalan (dari L/R) | F15: ='📋 Laporan Laba Rugi'!D23 -> 250000
B16: Total Aset Tetap (Net) | C16: =SUM(C13:C15) -> 41000000 | E16: Total Ekuitas | F16: =SUM(F13:F15) -> 65250000
A18: TOTAL ASET | C18: =C10+C16 -> 99450000 | D18: TOTAL LIABILITAS + EKUITAS | F18: =F10+F16 -> 191325000
